aliyunsdkeflo_controller/__init__.py
aliyunsdkeflo_controller/request/__init__.py
aliyunsdkeflo_controller/request/v20221215/ChangeResourceGroupRequest.py
aliyunsdkeflo_controller/request/v20221215/CreateClusterRequest.py
aliyunsdkeflo_controller/request/v20221215/DeleteClusterRequest.py
aliyunsdkeflo_controller/request/v20221215/DescribeClusterRequest.py
aliyunsdkeflo_controller/request/v20221215/DescribeNodeRequest.py
aliyunsdkeflo_controller/request/v20221215/DescribeRegionsRequest.py
aliyunsdkeflo_controller/request/v20221215/DescribeTaskRequest.py
aliyunsdkeflo_controller/request/v20221215/DescribeZonesRequest.py
aliyunsdkeflo_controller/request/v20221215/ExtendClusterRequest.py
aliyunsdkeflo_controller/request/v20221215/ListClusterNodesRequest.py
aliyunsdkeflo_controller/request/v20221215/ListClustersRequest.py
aliyunsdkeflo_controller/request/v20221215/ListFreeNodesRequest.py
aliyunsdkeflo_controller/request/v20221215/ListTagResourcesRequest.py
aliyunsdkeflo_controller/request/v20221215/RebootNodesRequest.py
aliyunsdkeflo_controller/request/v20221215/ReimageNodesRequest.py
aliyunsdkeflo_controller/request/v20221215/ShrinkClusterRequest.py
aliyunsdkeflo_controller/request/v20221215/TagResourcesRequest.py
aliyunsdkeflo_controller/request/v20221215/UntagResourcesRequest.py
aliyunsdkeflo_controller/request/v20221215/__init__.py
aliyun_python_sdk_eflo_controller-1.0.3.dist-info/LICENSE
aliyun_python_sdk_eflo_controller-1.0.3.dist-info/METADATA
aliyun_python_sdk_eflo_controller-1.0.3.dist-info/WHEEL
aliyun_python_sdk_eflo_controller-1.0.3.dist-info/top_level.txt
aliyun_python_sdk_eflo_controller-1.0.3.dist-info/RECORD
